wayback_machine_scraper/__init__.py
wayback_machine_scraper/__main__.py
wayback_machine_scraper/mirror_spider.py
wayback_machine_scraper-1.0.8.dist-info/LICENSE.txt
wayback_machine_scraper-1.0.8.dist-info/METADATA
wayback_machine_scraper-1.0.8.dist-info/WHEEL
wayback_machine_scraper-1.0.8.dist-info/entry_points.txt
wayback_machine_scraper-1.0.8.dist-info/top_level.txt
wayback_machine_scraper-1.0.8.dist-info/RECORD
