Metadata-Version: 2.1
Name: wayback-machine-scraper
Version: 1.0.8
Summary: A command-line utility for scraping Wayback Machine snapshots from archive.org.
Home-page: https://github.com/sangaline/wayback-machine-scraper
Author: Evan Sangaline
Author-email: evan@intoli.com
License: ISC
Keywords: archive.org scrapy scraper waybackmachine
Platform: UNKNOWN
Classifier: Development Status :: 5 - Production/Stable
Classifier: Framework :: Scrapy
Classifier: Topic :: Utilities
Classifier: License :: OSI Approved :: ISC License (ISCL)
Requires-Dist: cryptography
Requires-Dist: scrapy
Requires-Dist: scrapy-wayback-machine
Requires-Dist: twisted
